pyqs_mongo/__init__.py
pyqs_mongo/main.py
pyqs_mongo/parser.py
pyqs_mongo-0.0.1.dist-info/LICENSE
pyqs_mongo-0.0.1.dist-info/METADATA
pyqs_mongo-0.0.1.dist-info/WHEEL
pyqs_mongo-0.0.1.dist-info/top_level.txt
pyqs_mongo-0.0.1.dist-info/RECORD
