Metadata-Version: 2.1
Name: pyqs-mongo
Version: 0.0.1
Summary: A useful tool to parse the query string parameters on a resource into a MongoDB query object (compatible with PyMongo and MongoEngine).
Home-page: https://github.com/mrpycharm/pyqs-mongo
Author: Ahmed Pyar Ali
Author-email: ahmed.dhanani26@gmail.com
License: UNKNOWN
Platform: UNKNOWN
Classifier: Programming Language :: Python :: 3
Classifier: License :: OSI Approved :: MIT License
Classifier: Operating System :: OS Independent
Requires-Python: >=3.6
